langchain_graphrag/__init__.py
langchain_graphrag/py.typed
langchain_graphrag/indexing/__init__.py
langchain_graphrag/indexing/_graph_utils.py
langchain_graphrag/indexing/artifacts.py
langchain_graphrag/indexing/simple_indexer.py
langchain_graphrag/indexing/text_unit_extractor.py
langchain_graphrag/indexing/artifacts_generation/__init__.py
langchain_graphrag/indexing/artifacts_generation/entities.py
langchain_graphrag/indexing/artifacts_generation/relationships.py
langchain_graphrag/indexing/artifacts_generation/reports.py
langchain_graphrag/indexing/artifacts_generation/text_units.py
langchain_graphrag/indexing/embedding_generation/__init__.py
langchain_graphrag/indexing/embedding_generation/graph/__init__.py
langchain_graphrag/indexing/embedding_generation/graph/node2vec.py
langchain_graphrag/indexing/graph_clustering/__init__.py
langchain_graphrag/indexing/graph_clustering/leiden_community_detector.py
langchain_graphrag/indexing/graph_generation/__init__.py
langchain_graphrag/indexing/graph_generation/generator.py
langchain_graphrag/indexing/graph_generation/graphs_merger.py
langchain_graphrag/indexing/graph_generation/entity_relationship_extraction/__init__.py
langchain_graphrag/indexing/graph_generation/entity_relationship_extraction/_default_prompts.py
langchain_graphrag/indexing/graph_generation/entity_relationship_extraction/_output_parser.py
langchain_graphrag/indexing/graph_generation/entity_relationship_extraction/extractor.py
langchain_graphrag/indexing/graph_generation/entity_relationship_extraction/prompt_builder.py
langchain_graphrag/indexing/graph_generation/entity_relationship_summarization/__init__.py
langchain_graphrag/indexing/graph_generation/entity_relationship_summarization/_default_prompts.py
langchain_graphrag/indexing/graph_generation/entity_relationship_summarization/prompt_builder.py
langchain_graphrag/indexing/graph_generation/entity_relationship_summarization/summarizer.py
langchain_graphrag/indexing/report_generation/__init__.py
langchain_graphrag-0.0.9.dist-info/METADATA
langchain_graphrag-0.0.9.dist-info/WHEEL
langchain_graphrag-0.0.9.dist-info/licenses/LICENSE
langchain_graphrag-0.0.9.dist-info/RECORD
