Metadata-Version: 2.3
Name: langchain-graphrag
Version: 0.0.9
Summary: Implementation of GraphRAG (https://arxiv.org/pdf/2404.16130)
Author-email: Kapil Sachdeva <notan@email.com>
License-File: LICENSE
Requires-Python: >=3.10
Requires-Dist: graspologic>=3.4.1
Requires-Dist: langchain-core>=0.3.0
Requires-Dist: langchain-text-splitters>=0.3.0
Requires-Dist: networkx>=3.3
Requires-Dist: pandas>=2.2.2
Requires-Dist: tableprint>=0.9.1
